pybashrc/__init__.py
pybashrc/execute.py
pybashrc/post_setup.py
pybashrc/templates/.bashrc
pybashrc/templates/.pybashrc.py
pybashrc/templates/.pybashrc_aliases
pybashrc-1.2.0.dist-info/LICENSE
pybashrc-1.2.0.dist-info/METADATA
pybashrc-1.2.0.dist-info/WHEEL
pybashrc-1.2.0.dist-info/entry_points.txt
pybashrc-1.2.0.dist-info/top_level.txt
pybashrc-1.2.0.dist-info/RECORD
