Metadata-Version: 2.1
Name: pybashrc
Version: 1.2.0
Summary: Register python functions as bash commands
Home-page: https://github.com/jneeven/pybashrc
Author: Jelmer Neeven
Author-email: jelmer@neeven.tech
License: UNKNOWN
Platform: UNKNOWN
Classifier: Programming Language :: Python :: 3
Classifier: License :: OSI Approved :: MIT License
Classifier: Operating System :: Unix 
Requires-Python: >=3.6
Requires-Dist: click (<8.0,>=7.0)
